bridge/__init__.py
bridge/bridge.py
aitools_bridge-0.0.1.dist-info/LICENSE
aitools_bridge-0.0.1.dist-info/METADATA
aitools_bridge-0.0.1.dist-info/WHEEL
aitools_bridge-0.0.1.dist-info/RECORD
