Metadata-Version: 2.3
Name: aitools-bridge
Version: 0.0.1
Summary: aitools-bridge is a minimalist framework (or a decorator) designed to seamlessly integrate existing tools with the advanced AI ecosystem.
License: Apache-2.0
Author: m0reA1
Author-email: more.aitools@gmail.com
Requires-Python: >=3.9
Classifier: Programming Language :: Python
Classifier: License :: OSI Approved :: Apache Software License
Classifier: Topic :: Scientific/Engineering :: Artificial Intelligence
Classifier: Topic :: Software Development :: Libraries
Requires-Dist: griffe (==1.6.0)
Requires-Dist: jsonref (==1.1.0)
Requires-Dist: pydantic (==2.10.6)
Project-URL: Homepage, https://github.com/m0reA1/aitools-bridge
